odoo8_addon_product_attribute_multi_type-8.0.1.0.0-py2.7-nspkg.pth
odoo_addons/product_attribute_multi_type/__openerp__.py
odoo_addons/product_attribute_multi_type/__init__.py
odoo_addons/product_attribute_multi_type/README.rst
odoo_addons/product_attribute_multi_type/models/product.py
odoo_addons/product_attribute_multi_type/models/__init__.py
odoo_addons/product_attribute_multi_type/i18n/es.po
odoo_addons/product_attribute_multi_type/i18n/product_attribute_multi_type.pot
odoo_addons/product_attribute_multi_type/views/product_view.xml
odoo_addons/product_attribute_multi_type/data/product_attribute_data.xml
odoo_addons/product_attribute_multi_type/static/description/icon.png
odoo8_addon_product_attribute_multi_type-8.0.1.0.0.dist-info/top_level.txt
odoo8_addon_product_attribute_multi_type-8.0.1.0.0.dist-info/WHEEL
odoo8_addon_product_attribute_multi_type-8.0.1.0.0.dist-info/RECORD
odoo8_addon_product_attribute_multi_type-8.0.1.0.0.dist-info/metadata.json
odoo8_addon_product_attribute_multi_type-8.0.1.0.0.dist-info/DESCRIPTION.rst
odoo8_addon_product_attribute_multi_type-8.0.1.0.0.dist-info/METADATA
odoo8_addon_product_attribute_multi_type-8.0.1.0.0.dist-info/namespace_packages.txt
