Metadata-Version: 2.0
Name: odoo8-addon-product-attribute-multi-type
Version: 8.0.1.0.0
Summary: Product attribute types
Home-page: http://www.odoomrp.com
Author: UNKNOWN
Author-email: UNKNOWN
License: UNKNOWN
Platform: UNKNOWN
Requires-Dist: odoo (<9.0a,>=8.0a)
Classifier: Programming Language :: Python :: 2.7
Classifier: Framework :: Odoo
